buildbot_waterfall_view/VERSION
buildbot_waterfall_view/__init__.py
buildbot_waterfall_view/static/scripts.js
buildbot_waterfall_view/static/styles.css
buildbot_waterfall_view-4.3.0.dist-info/METADATA
buildbot_waterfall_view-4.3.0.dist-info/WHEEL
buildbot_waterfall_view-4.3.0.dist-info/entry_points.txt
buildbot_waterfall_view-4.3.0.dist-info/top_level.txt
buildbot_waterfall_view-4.3.0.dist-info/RECORD
